[
  {
    "": "DMRGD",
    "Adet": 14,
    "Alis Fiyati": 10.24,
    "Maliyet (TL)": 143.36,
    "Guncel Fiyat": 15.16,
    "Guncel Getiri": 212.24,
    "Net Kar-Zarar (tl)": 68.88,
    "% Kar- Zarar": 0.48046875,
    "SatisFiyati": "",
    "Satildi mi ?": false
  },
  {
    "": "MHRGY",
    "Adet": 65,
    "Alis Fiyati": 4.3,
    "Maliyet (TL)": 279.5,
    "Guncel Fiyat": 4.97,
    "Guncel Getiri": 323.05,
    "Net Kar-Zarar (tl)": 43.55000000000001,
    "% Kar- Zarar": 0.15581395348837218,
    "SatisFiyati": "",
    "Satildi mi ?": false
  },
  {
    "": "MARBL",
    "Adet": 21,
    "Alis Fiyati": 10.97,
    "Maliyet (TL)": 230.37,
    "Guncel Fiyat": 16.69,
    "Guncel Getiri": 350.49,
    "Net Kar-Zarar (tl)": 120.12,
    "% Kar- Zarar": 0.5214220601640838,
    "SatisFiyati": "",
    "Satildi mi ?": false
  },
  {
    "": "PATEK",
    "Adet": 8,
    "Alis Fiyati": 35,
    "Maliyet (TL)": 280,
    "Guncel Fiyat": 82.3,
    "Guncel Getiri": 658.4,
    "Net Kar-Zarar (tl)": 378.4,
    "% Kar- Zarar": 1.3514285714285714,
    "SatisFiyati": "132.4",
    "Satildi mi ?": true
  },
  {
    "": "BORSK",
    "Adet": 16,
    "Alis Fiyati": 26.54,
    "Maliyet (TL)": 424.64,
    "Guncel Fiyat": 33.34,
    "Guncel Getiri": 533.44,
    "Net Kar-Zarar (tl)": 108.80000000000007,
    "% Kar- Zarar": 0.25621703089675973,
    "SatisFiyati": "",
    "Satildi mi ?": false
  },
  {
    "": "MOGAN",
    "Adet": 68,
    "Alis Fiyati": 11.33,
    "Maliyet (TL)": 770.44,
    "Guncel Fiyat": 15.33,
    "Guncel Getiri": 1042.44,
    "Net Kar-Zarar (tl)": 272,
    "% Kar- Zarar": 0.353045013239188,
    "SatisFiyati": "",
    "Satildi mi ?": false
  },
  {
    "": "",
    "Adet": "",
    "Alis Fiyati": "",
    "Maliyet (TL)": "",
    "Guncel Fiyat": "",
    "Guncel Getiri": "",
    "Net Kar-Zarar (tl)": "",
    "% Kar- Zarar": "",
    "SatisFiyati": "",
    "Satildi mi ?": ""
  },
  {
    "": "",
    "Adet": "",
    "Alis Fiyati": "",
    "Maliyet (TL)": "",
    "Guncel Fiyat": "",
    "Guncel Getiri": "",
    "Net Kar-Zarar (tl)": "",
    "% Kar- Zarar": "",
    "SatisFiyati": "",
    "Satildi mi ?": ""
  },
  {
    "": "",
    "Adet": "",
    "Alis Fiyati": "",
    "Maliyet (TL)": "",
    "Guncel Fiyat": "",
    "Guncel Getiri": "",
    "Net Kar-Zarar (tl)": "",
    "% Kar- Zarar": "",
    "SatisFiyati": "",
    "Satildi mi ?": ""
  },
  {
    "": "",
    "Adet": "",
    "Alis Fiyati": "",
    "Maliyet (TL)": "",
    "Guncel Fiyat": "",
    "Guncel Getiri": "",
    "Net Kar-Zarar (tl)": "",
    "% Kar- Zarar": "",
    "SatisFiyati": "",
    "Satildi mi ?": ""
  },
  {
    "": "",
    "Adet": "",
    "Alis Fiyati": "",
    "Maliyet (TL)": "",
    "Guncel Fiyat": "",
    "Guncel Getiri": "",
    "Net Kar-Zarar (tl)": "",
    "% Kar- Zarar": "",
    "SatisFiyati": "",
    "Satildi mi ?": ""
  },
  {
    "": "",
    "Adet": "",
    "Alis Fiyati": "",
    "Maliyet (TL)": "",
    "Guncel Fiyat": "",
    "Guncel Getiri": "",
    "Net Kar-Zarar (tl)": "",
    "% Kar- Zarar": "",
    "SatisFiyati": "",
    "Satildi mi ?": ""
  },
  {
    "": "Toplam",
    "Adet": 0,
    "Alis Fiyati": 0,
    "Maliyet (TL)": 1848.31,
    "Guncel Fiyat": 0,
    "Guncel Getiri": 2461.66,
    "Net Kar-Zarar (tl)": 613.3499999999999,
    "% Kar- Zarar": 0.33184368423045896,
    "SatisFiyati": "",
    "Satildi mi ?": ""
  },
  {
    "": "",
    "Adet": "",
    "Alis Fiyati": "",
    "Maliyet (TL)": "",
    "Guncel Fiyat": "",
    "Guncel Getiri": "",
    "Net Kar-Zarar (tl)": "",
    "% Kar- Zarar": "",
    "SatisFiyati": "",
    "Satildi mi ?": ""
  },
  {
    "": "",
    "Adet": "",
    "Alis Fiyati": "",
    "Maliyet (TL)": "",
    "Guncel Fiyat": "",
    "Guncel Getiri": "",
    "Net Kar-Zarar (tl)": "",
    "% Kar- Zarar": "",
    "SatisFiyati": "",
    "Satildi mi ?": ""
  },
  {
    "": "",
    "Adet": "",
    "Alis Fiyati": "",
    "Maliyet (TL)": "",
    "Guncel Fiyat": "",
    "Guncel Getiri": "",
    "Net Kar-Zarar (tl)": "",
    "% Kar- Zarar": "",
    "SatisFiyati": "",
    "Satildi mi ?": ""
  },
  {
    "": "",
    "Adet": "",
    "Alis Fiyati": "",
    "Maliyet (TL)": "",
    "Guncel Fiyat": "x zx x",
    "Guncel Getiri": "",
    "Net Kar-Zarar (tl)": "",
    "% Kar- Zarar": "",
    "SatisFiyati": "",
    "Satildi mi ?": ""
  },
  {
    "": "",
    "Adet": "",
    "Alis Fiyati": "",
    "Maliyet (TL)": "",
    "Guncel Fiyat": "",
    "Guncel Getiri": "",
    "Net Kar-Zarar (tl)": "",
    "% Kar- Zarar": "",
    "SatisFiyati": "",
    "Satildi mi ?": ""
  },
  {
    "": "",
    "Adet": "",
    "Alis Fiyati": "",
    "Maliyet (TL)": "",
    "Guncel Fiyat": "",
    "Guncel Getiri": "",
    "Net Kar-Zarar (tl)": "",
    "% Kar- Zarar": "",
    "SatisFiyati": "",
    "Satildi mi ?": ""
  },
  {
    "": "",
    "Adet": "",
    "Alis Fiyati": "",
    "Maliyet (TL)": "",
    "Guncel Fiyat": "",
    "Guncel Getiri": "",
    "Net Kar-Zarar (tl)": "",
    "% Kar- Zarar": "",
    "SatisFiyati": "",
    "Satildi mi ?": false
  }
]