[
  {
    "": "DMRGD",
    "Adet": 14,
    "Alis Fiyati": 10.24,
    "Maliyet (TL)": 143.36,
    "Guncel Fiyat": 11.12,
    "Guncel Getiri": 155.67999999999998,
    "Net Kar-Zarar (tl)": 12.319999999999965,
    "% Kar- Zarar": 0.08593749999999972,
    "SatisFiyati": "",
    "Satildi mi ?": false
  },
  {
    "": "MHRGY",
    "Adet": 65,
    "Alis Fiyati": 4.3,
    "Maliyet (TL)": 279.5,
    "Guncel Fiyat": 4.6,
    "Guncel Getiri": 299,
    "Net Kar-Zarar (tl)": 19.5,
    "% Kar- Zarar": 0.06976744186046503,
    "SatisFiyati": "",
    "Satildi mi ?": true
  },
  {
    "": "MARBL",
    "Adet": 21,
    "Alis Fiyati": 10.97,
    "Maliyet (TL)": 230.37,
    "Guncel Fiyat": 12.42,
    "Guncel Getiri": 260.82,
    "Net Kar-Zarar (tl)": 30.44999999999999,
    "% Kar- Zarar": 0.13217866909753867,
    "SatisFiyati": "",
    "Satildi mi ?": true
  },
  {
    "": "PATEK",
    "Adet": 8,
    "Alis Fiyati": 35,
    "Maliyet (TL)": 280,
    "Guncel Fiyat": 112.2,
    "Guncel Getiri": 897.6,
    "Net Kar-Zarar (tl)": 617.6,
    "% Kar- Zarar": 2.205714285714286,
    "SatisFiyati": "132.4",
    "Satildi mi ?": true
  },
  {
    "": "BORSK",
    "Adet": 16,
    "Alis Fiyati": 26.54,
    "Maliyet (TL)": 424.64,
    "Guncel Fiyat": 22.2,
    "Guncel Getiri": 355.2,
    "Net Kar-Zarar (tl)": -69.44,
    "% Kar- Zarar": -0.16352675207234368,
    "SatisFiyati": "",
    "Satildi mi ?": true
  },
  {
    "": "MOGAN",
    "Adet": 68,
    "Alis Fiyati": 11.33,
    "Maliyet (TL)": 770.44,
    "Guncel Fiyat": 10.39,
    "Guncel Getiri": 706.52,
    "Net Kar-Zarar (tl)": -63.92000000000007,
    "% Kar- Zarar": -0.08296557811120935,
    "SatisFiyati": "",
    "Satildi mi ?": true
  },
  {
    "": "",
    "Adet": "",
    "Alis Fiyati": "",
    "Maliyet (TL)": "",
    "Guncel Fiyat": "",
    "Guncel Getiri": "",
    "Net Kar-Zarar (tl)": "",
    "% Kar- Zarar": "",
    "SatisFiyati": "",
    "Satildi mi ?": ""
  },
  {
    "": "",
    "Adet": "",
    "Alis Fiyati": "",
    "Maliyet (TL)": "",
    "Guncel Fiyat": "",
    "Guncel Getiri": "",
    "Net Kar-Zarar (tl)": "",
    "% Kar- Zarar": "",
    "SatisFiyati": "",
    "Satildi mi ?": ""
  },
  {
    "": "",
    "Adet": "",
    "Alis Fiyati": "",
    "Maliyet (TL)": "",
    "Guncel Fiyat": "",
    "Guncel Getiri": "",
    "Net Kar-Zarar (tl)": "",
    "% Kar- Zarar": "",
    "SatisFiyati": "",
    "Satildi mi ?": ""
  },
  {
    "": "",
    "Adet": "",
    "Alis Fiyati": "",
    "Maliyet (TL)": "",
    "Guncel Fiyat": "",
    "Guncel Getiri": "",
    "Net Kar-Zarar (tl)": "",
    "% Kar- Zarar": "",
    "SatisFiyati": "",
    "Satildi mi ?": ""
  },
  {
    "": "",
    "Adet": "",
    "Alis Fiyati": "",
    "Maliyet (TL)": "",
    "Guncel Fiyat": "",
    "Guncel Getiri": "",
    "Net Kar-Zarar (tl)": "",
    "% Kar- Zarar": "",
    "SatisFiyati": "",
    "Satildi mi ?": ""
  },
  {
    "": "",
    "Adet": "",
    "Alis Fiyati": "",
    "Maliyet (TL)": "",
    "Guncel Fiyat": "",
    "Guncel Getiri": "",
    "Net Kar-Zarar (tl)": "",
    "% Kar- Zarar": "",
    "SatisFiyati": "",
    "Satildi mi ?": ""
  },
  {
    "": "Toplam",
    "Adet": 0,
    "Alis Fiyati": 0,
    "Maliyet (TL)": 143.36,
    "Guncel Fiyat": 0,
    "Guncel Getiri": 155.67999999999998,
    "Net Kar-Zarar (tl)": 12.319999999999965,
    "% Kar- Zarar": 0.08593749999999972,
    "SatisFiyati": "",
    "Satildi mi ?": ""
  },
  {
    "": "",
    "Adet": "",
    "Alis Fiyati": "",
    "Maliyet (TL)": "",
    "Guncel Fiyat": "",
    "Guncel Getiri": "",
    "Net Kar-Zarar (tl)": "",
    "% Kar- Zarar": "",
    "SatisFiyati": "",
    "Satildi mi ?": ""
  },
  {
    "": "",
    "Adet": "",
    "Alis Fiyati": "",
    "Maliyet (TL)": "",
    "Guncel Fiyat": "",
    "Guncel Getiri": "",
    "Net Kar-Zarar (tl)": "",
    "% Kar- Zarar": "",
    "SatisFiyati": "",
    "Satildi mi ?": ""
  },
  {
    "": "",
    "Adet": "",
    "Alis Fiyati": "",
    "Maliyet (TL)": "",
    "Guncel Fiyat": "",
    "Guncel Getiri": "",
    "Net Kar-Zarar (tl)": "",
    "% Kar- Zarar": "",
    "SatisFiyati": "",
    "Satildi mi ?": ""
  },
  {
    "": "",
    "Adet": "",
    "Alis Fiyati": "",
    "Maliyet (TL)": "",
    "Guncel Fiyat": "x zx x",
    "Guncel Getiri": "",
    "Net Kar-Zarar (tl)": "",
    "% Kar- Zarar": "",
    "SatisFiyati": "",
    "Satildi mi ?": ""
  },
  {
    "": "",
    "Adet": "",
    "Alis Fiyati": "",
    "Maliyet (TL)": "",
    "Guncel Fiyat": "",
    "Guncel Getiri": "",
    "Net Kar-Zarar (tl)": "",
    "% Kar- Zarar": "",
    "SatisFiyati": "",
    "Satildi mi ?": ""
  },
  {
    "": "",
    "Adet": "",
    "Alis Fiyati": "",
    "Maliyet (TL)": "",
    "Guncel Fiyat": "",
    "Guncel Getiri": "",
    "Net Kar-Zarar (tl)": "",
    "% Kar- Zarar": "",
    "SatisFiyati": "",
    "Satildi mi ?": ""
  },
  {
    "": "",
    "Adet": "",
    "Alis Fiyati": "",
    "Maliyet (TL)": "",
    "Guncel Fiyat": "",
    "Guncel Getiri": "",
    "Net Kar-Zarar (tl)": "",
    "% Kar- Zarar": "",
    "SatisFiyati": "",
    "Satildi mi ?": false
  }
]