[
  {
    "Adi": "BYDNR",
    "Adet": 14,
    "Alis Fiyati": 21,
    "Maliyet (TL)": 294,
    "Guncel Fiyat": 44.08,
    "Guncel Getiri": 617.12,
    "Net Kar-Zarar (tl)": 323.12,
    "% Kar- Zarar": 1.099047619047619,
    "": "BYDNR",
    "Satildi mi ?": false
  },
  {
    "Adi": "ENERY",
    "Adet": 11,
    "Alis Fiyati": 88.76,
    "Maliyet (TL)": 976.36,
    "Guncel Fiyat": 153.5,
    "Guncel Getiri": 1688.5,
    "Net Kar-Zarar (tl)": 712.14,
    "% Kar- Zarar": 0.7293826047769266,
    "": "ENERY",
    "Satildi mi ?": false
  },
  {
    "Adi": "IZENR",
    "Adet": 36,
    "Alis Fiyati": 19,
    "Maliyet (TL)": 684,
    "Guncel Fiyat": 47.72,
    "Guncel Getiri": 1717.92,
    "Net Kar-Zarar (tl)": 1033.92,
    "% Kar- Zarar": 1.5115789473684211,
    "": "IZENR",
    "Satildi mi ?": false
  },
  {
    "Adi": "KZGYO",
    "Adet": 14,
    "Alis Fiyati": 20.76,
    "Maliyet (TL)": 290.64000000000004,
    "Guncel Fiyat": 32.24,
    "Guncel Getiri": 451.36,
    "Net Kar-Zarar (tl)": 160.71999999999997,
    "% Kar- Zarar": 0.5529865125240846,
    "": "KZGYO",
    "Satildi mi ?": false
  },
  {
    "Adi": "TATEN",
    "Adet": 22,
    "Alis Fiyati": 22.5,
    "Maliyet (TL)": 495,
    "Guncel Fiyat": 52.4,
    "Guncel Getiri": 1152.8,
    "Net Kar-Zarar (tl)": 657.8,
    "% Kar- Zarar": 1.3288888888888888,
    "": "TATEN",
    "Satildi mi ?": false
  },
  {
    "Adi": "EBEBK",
    "Adet": 5,
    "Alis Fiyati": 46.5,
    "Maliyet (TL)": 232.5,
    "Guncel Fiyat": 76.35,
    "Guncel Getiri": 381.75,
    "Net Kar-Zarar (tl)": 149.25,
    "% Kar- Zarar": 0.6419354838709677,
    "": "EBEBK",
    "Satildi mi ?": false
  },
  {
    "Adi": "TARKM",
    "Adet": 1,
    "Alis Fiyati": 107.5,
    "Maliyet (TL)": 107.5,
    "Guncel Fiyat": 209.3,
    "Guncel Getiri": 209.3,
    "Net Kar-Zarar (tl)": 101.80000000000001,
    "% Kar- Zarar": 0.9469767441860466,
    "": "TARKM",
    "Satildi mi ?": false
  },
  {
    "Adi": "GIPTA",
    "Adet": 9,
    "Alis Fiyati": 20.9,
    "Maliyet (TL)": 188.1,
    "Guncel Fiyat": 33.58,
    "Guncel Getiri": 302.21999999999997,
    "Net Kar-Zarar (tl)": 114.11999999999998,
    "% Kar- Zarar": 0.6066985645933013,
    "": "GIPTA",
    "Satildi mi ?": false
  },
  {
    "Adi": "",
    "Adet": "",
    "Alis Fiyati": "",
    "Maliyet (TL)": "",
    "Guncel Fiyat": "",
    "Guncel Getiri": "",
    "Net Kar-Zarar (tl)": "",
    "% Kar- Zarar": "",
    "": "",
    "Satildi mi ?": false
  },
  {
    "Adi": "Toplam",
    "Adet": 0,
    "Alis Fiyati": 0,
    "Maliyet (TL)": 3268.1,
    "Guncel Fiyat": 0,
    "Guncel Getiri": 6520.97,
    "Net Kar-Zarar (tl)": 3252.8700000000003,
    "% Kar- Zarar": 0,
    "": "",
    "Satildi mi ?": false
  }
]