[
  {
    "": "",
    "Adet": 75,
    "Alis Fiyati": 5.21,
    "Maliyet (TL)": 390.75,
    "Guncel Fiyat": 11.76,
    "Guncel Getiri": 882,
    "Net Kar-Zarar (tl)": 491.25,
    "% Kar- Zarar": 1.257197696737044,
    "Satildi mi ?": false
  },
  {
    "": "",
    "Adet": 3,
    "Alis Fiyati": 125,
    "Maliyet (TL)": 375,
    "Guncel Fiyat": 241.6,
    "Guncel Getiri": 724.8,
    "Net Kar-Zarar (tl)": 349.79999999999995,
    "% Kar- Zarar": 0.9327999999999997,
    "Satildi mi ?": false
  },
  {
    "": "",
    "Adet": 14,
    "Alis Fiyati": 10.24,
    "Maliyet (TL)": 143.36,
    "Guncel Fiyat": 10.21,
    "Guncel Getiri": 142.94,
    "Net Kar-Zarar (tl)": -0.4200000000000159,
    "% Kar- Zarar": -0.0029296875000001422,
    "Satildi mi ?": false
  },
  {
    "": "",
    "Adet": 11,
    "Alis Fiyati": 88.76,
    "Maliyet (TL)": 976.36,
    "Guncel Fiyat": 111.8,
    "Guncel Getiri": 1229.8,
    "Net Kar-Zarar (tl)": 253.43999999999994,
    "% Kar- Zarar": 0.25957638575935094,
    "Satildi mi ?": false
  },
  {
    "": "",
    "Adet": 18,
    "Alis Fiyati": 12.77,
    "Maliyet (TL)": 229.85999999999999,
    "Guncel Fiyat": 34.38,
    "Guncel Getiri": 618.84,
    "Net Kar-Zarar (tl)": 388.98,
    "% Kar- Zarar": 1.692247454972592,
    "Satildi mi ?": false
  },
  {
    "": "IZENR",
    "Adet": 36,
    "Alis Fiyati": 19,
    "Maliyet (TL)": 684,
    "Guncel Fiyat": 26.26,
    "Guncel Getiri": 945.36,
    "Net Kar-Zarar (tl)": 261.36,
    "% Kar- Zarar": 0.3821052631578948,
    "Satildi mi ?": false
  },
  {
    "": "",
    "Adet": 65,
    "Alis Fiyati": 4.3,
    "Maliyet (TL)": 279.5,
    "Guncel Fiyat": 5.11,
    "Guncel Getiri": 332.15000000000003,
    "Net Kar-Zarar (tl)": 52.650000000000034,
    "% Kar- Zarar": 0.1883720930232559,
    "Satildi mi ?": false
  },
  {
    "": "",
    "Adet": 46,
    "Alis Fiyati": 9.3,
    "Maliyet (TL)": 427.8,
    "Guncel Fiyat": 21.1,
    "Guncel Getiri": 970.6,
    "Net Kar-Zarar (tl)": 542.8,
    "% Kar- Zarar": 1.2688172043010755,
    "Satildi mi ?": false
  },
  {
    "": "TATEN",
    "Adet": 22,
    "Alis Fiyati": 22.5,
    "Maliyet (TL)": 495,
    "Guncel Fiyat": 30.4,
    "Guncel Getiri": 668.8,
    "Net Kar-Zarar (tl)": 173.79999999999995,
    "% Kar- Zarar": 0.3511111111111109,
    "Satildi mi ?": false
  },
  {
    "": "",
    "Adet": 9,
    "Alis Fiyati": 130,
    "Maliyet (TL)": 1170,
    "Guncel Fiyat": 117.4,
    "Guncel Getiri": 1056.6000000000001,
    "Net Kar-Zarar (tl)": -113.39999999999986,
    "% Kar- Zarar": -0.09692307692307679,
    "Satildi mi ?": ""
  },
  {
    "": "",
    "Adet": 10,
    "Alis Fiyati": 15.78,
    "Maliyet (TL)": 157.79999999999998,
    "Guncel Fiyat": 20,
    "Guncel Getiri": 200,
    "Net Kar-Zarar (tl)": 42.20000000000002,
    "% Kar- Zarar": 0.26742712294043103,
    "Satildi mi ?": ""
  },
  {
    "": "",
    "Adet": 21,
    "Alis Fiyati": 10.97,
    "Maliyet (TL)": 230.37,
    "Guncel Fiyat": 13.34,
    "Guncel Getiri": 280.14,
    "Net Kar-Zarar (tl)": 49.76999999999998,
    "% Kar- Zarar": 0.2160437556973565,
    "Satildi mi ?": ""
  },
  {
    "": "",
    "Adet": 0,
    "Alis Fiyati": 0,
    "Maliyet (TL)": 5559.8,
    "Guncel Fiyat": 0,
    "Guncel Getiri": 8052.030000000001,
    "Net Kar-Zarar (tl)": 2492.2300000000005,
    "% Kar- Zarar": 0.4482589301773444,
    "Satildi mi ?": false
  },
  {
    "": "",
    "Adet": "",
    "Alis Fiyati": "",
    "Maliyet (TL)": "",
    "Guncel Fiyat": "",
    "Guncel Getiri": "",
    "Net Kar-Zarar (tl)": "",
    "% Kar- Zarar": "",
    "Satildi mi ?": ""
  },
  {
    "": "",
    "Adet": "",
    "Alis Fiyati": "",
    "Maliyet (TL)": "",
    "Guncel Fiyat": "",
    "Guncel Getiri": "",
    "Net Kar-Zarar (tl)": "",
    "% Kar- Zarar": "",
    "Satildi mi ?": ""
  },
  {
    "": "",
    "Adet": "",
    "Alis Fiyati": "",
    "Maliyet (TL)": "",
    "Guncel Fiyat": "",
    "Guncel Getiri": "",
    "Net Kar-Zarar (tl)": "",
    "% Kar- Zarar": "",
    "Satildi mi ?": ""
  },
  {
    "": "",
    "Adet": "",
    "Alis Fiyati": "",
    "Maliyet (TL)": "",
    "Guncel Fiyat": "",
    "Guncel Getiri": "",
    "Net Kar-Zarar (tl)": "",
    "% Kar- Zarar": "",
    "Satildi mi ?": ""
  },
  {
    "": "",
    "Adet": "",
    "Alis Fiyati": "",
    "Maliyet (TL)": "",
    "Guncel Fiyat": "",
    "Guncel Getiri": "",
    "Net Kar-Zarar (tl)": "",
    "% Kar- Zarar": "",
    "Satildi mi ?": ""
  },
  {
    "": "",
    "Adet": "",
    "Alis Fiyati": "",
    "Maliyet (TL)": "",
    "Guncel Fiyat": "",
    "Guncel Getiri": "",
    "Net Kar-Zarar (tl)": "",
    "% Kar- Zarar": "",
    "Satildi mi ?": ""
  },
  {
    "": "",
    "Adet": "",
    "Alis Fiyati": "",
    "Maliyet (TL)": "",
    "Guncel Fiyat": "",
    "Guncel Getiri": "",
    "Net Kar-Zarar (tl)": "",
    "% Kar- Zarar": "",
    "Satildi mi ?": false
  }
]