[
  {
    "Adi": "BORLS",
    "Adet": 10,
    "Alis Fiyati": 25.29,
    "Maliyet (TL)": 252.89999999999998,
    "Guncel Fiyat": 37.02,
    "Guncel Getiri": 370.20000000000005,
    "Net Kar-Zarar (tl)": 117.30000000000007,
    "% Kar- Zarar": 0.46381969157769903,
    "": "",
    "Satildi mi ?": false
  },
  {
    "Adi": "BYDNR",
    "Adet": 14,
    "Alis Fiyati": 21,
    "Maliyet (TL)": 294,
    "Guncel Fiyat": 31.34,
    "Guncel Getiri": 438.76,
    "Net Kar-Zarar (tl)": 144.76,
    "% Kar- Zarar": 0.4923809523809524,
    "": "BYDNR",
    "Satildi mi ?": false
  },
  {
    "Adi": "DMRGD",
    "Adet": 14,
    "Alis Fiyati": 10.24,
    "Maliyet (TL)": 143.36,
    "Guncel Fiyat": 15.06,
    "Guncel Getiri": 210.84,
    "Net Kar-Zarar (tl)": 67.47999999999999,
    "% Kar- Zarar": 0.4707031249999997,
    "": "",
    "Satildi mi ?": false
  },
  {
    "Adi": "DOFER",
    "Adet": 5,
    "Alis Fiyati": 17.1,
    "Maliyet (TL)": 85.5,
    "Guncel Fiyat": 33.28,
    "Guncel Getiri": 166.4,
    "Net Kar-Zarar (tl)": 80.9,
    "% Kar- Zarar": 0.9461988304093566,
    "": "",
    "Satildi mi ?": false
  },
  {
    "Adi": "EBEBK",
    "Adet": 5,
    "Alis Fiyati": 46.5,
    "Maliyet (TL)": 232.5,
    "Guncel Fiyat": 65.55,
    "Guncel Getiri": 327.75,
    "Net Kar-Zarar (tl)": 95.25,
    "% Kar- Zarar": 0.4096774193548387,
    "": "EBEBK",
    "Satildi mi ?": false
  },
  {
    "Adi": "ENERY",
    "Adet": 11,
    "Alis Fiyati": 88.76,
    "Maliyet (TL)": 976.36,
    "Guncel Fiyat": 143.3,
    "Guncel Getiri": 1576.3000000000002,
    "Net Kar-Zarar (tl)": 599.9400000000002,
    "% Kar- Zarar": 0.6144659756647138,
    "": "lll",
    "Satildi mi ?": false
  },
  {
    "Adi": "GIPTA",
    "Adet": 9,
    "Alis Fiyati": 20.9,
    "Maliyet (TL)": 188.1,
    "Guncel Fiyat": 31.7,
    "Guncel Getiri": 285.3,
    "Net Kar-Zarar (tl)": 97.20000000000002,
    "% Kar- Zarar": 0.5167464114832535,
    "": "",
    "Satildi mi ?": false
  },
  {
    "Adi": "HATSN",
    "Adet": 9,
    "Alis Fiyati": 22.6,
    "Maliyet (TL)": 203.4,
    "Guncel Fiyat": 63.85,
    "Guncel Getiri": 574.65,
    "Net Kar-Zarar (tl)": 371.25,
    "% Kar- Zarar": 1.825221238938053,
    "": "",
    "Satildi mi ?": false
  },
  {
    "Adi": "IZENR",
    "Adet": 36,
    "Alis Fiyati": 19,
    "Maliyet (TL)": 684,
    "Guncel Fiyat": 36.44,
    "Guncel Getiri": 1311.84,
    "Net Kar-Zarar (tl)": 627.8399999999999,
    "% Kar- Zarar": 0.9178947368421052,
    "": "IZENR",
    "Satildi mi ?": false
  },
  {
    "Adi": "KZGYO",
    "Adet": 14,
    "Alis Fiyati": 20.76,
    "Maliyet (TL)": 290.64000000000004,
    "Guncel Fiyat": 25.66,
    "Guncel Getiri": 359.24,
    "Net Kar-Zarar (tl)": 68.59999999999997,
    "% Kar- Zarar": 0.23603082851637752,
    "": "KZGYO",
    "Satildi mi ?": false
  },
  {
    "Adi": "MHRGY",
    "Adet": 65,
    "Alis Fiyati": 4.3,
    "Maliyet (TL)": 279.5,
    "Guncel Fiyat": 6.91,
    "Guncel Getiri": 449.15000000000003,
    "Net Kar-Zarar (tl)": 169.65000000000003,
    "% Kar- Zarar": 0.6069767441860466,
    "": "",
    "Satildi mi ?": false
  },
  {
    "Adi": "REEDR",
    "Adet": 46,
    "Alis Fiyati": 9.3,
    "Maliyet (TL)": 427.8,
    "Guncel Fiyat": 16.84,
    "Guncel Getiri": 774.64,
    "Net Kar-Zarar (tl)": 346.84,
    "% Kar- Zarar": 0.8107526881720429,
    "": "",
    "Satildi mi ?": false
  },
  {
    "Adi": "TARKM",
    "Adet": 1,
    "Alis Fiyati": 107.5,
    "Maliyet (TL)": 107.5,
    "Guncel Fiyat": 772.6,
    "Guncel Getiri": 772.6,
    "Net Kar-Zarar (tl)": 665.1,
    "% Kar- Zarar": 6.186976744186046,
    "": "TARKM",
    "Satildi mi ?": false
  },
  {
    "Adi": "TATEN",
    "Adet": 22,
    "Alis Fiyati": 22.5,
    "Maliyet (TL)": 495,
    "Guncel Fiyat": 39.56,
    "Guncel Getiri": 870.32,
    "Net Kar-Zarar (tl)": 375.32000000000005,
    "% Kar- Zarar": 0.7582222222222222,
    "": "TATEN",
    "Satildi mi ?": false
  },
  {
    "Adi": "Toplam",
    "Adet": 0,
    "Alis Fiyati": 0,
    "Maliyet (TL)": 4165.5599999999995,
    "Guncel Fiyat": 0,
    "Guncel Getiri": 7617.67,
    "Net Kar-Zarar (tl)": 3452.1100000000006,
    "% Kar- Zarar": 0.8287265097609929,
    "": "",
    "Satildi mi ?": false
  },
  {
    "Adi": "",
    "Adet": "",
    "Alis Fiyati": "",
    "Maliyet (TL)": "",
    "Guncel Fiyat": "",
    "Guncel Getiri": "",
    "Net Kar-Zarar (tl)": "",
    "% Kar- Zarar": "",
    "": "",
    "Satildi mi ?": false
  }
]