[
  {
    "": "DMRGD",
    "Adet": 14,
    "Alis Fiyati": 10.24,
    "Maliyet (TL)": 143.36,
    "Guncel Fiyat": 14.16,
    "Guncel Getiri": 198.24,
    "Net Kar-Zarar (tl)": 54.879999999999995,
    "% Kar- Zarar": 0.3828125,
    "SatisFiyati": "",
    "Satildi mi ?": false
  },
  {
    "": "MHRGY",
    "Adet": 65,
    "Alis Fiyati": 4.3,
    "Maliyet (TL)": 279.5,
    "Guncel Fiyat": 4.69,
    "Guncel Getiri": 304.85,
    "Net Kar-Zarar (tl)": 25.350000000000023,
    "% Kar- Zarar": 0.09069767441860478,
    "SatisFiyati": "",
    "Satildi mi ?": false
  },
  {
    "": "MARBL",
    "Adet": 21,
    "Alis Fiyati": 10.97,
    "Maliyet (TL)": 230.37,
    "Guncel Fiyat": 14.73,
    "Guncel Getiri": 309.33,
    "Net Kar-Zarar (tl)": 78.95999999999998,
    "% Kar- Zarar": 0.3427529626253417,
    "SatisFiyati": "",
    "Satildi mi ?": false
  },
  {
    "": "PATEK",
    "Adet": 8,
    "Alis Fiyati": 35,
    "Maliyet (TL)": 280,
    "Guncel Fiyat": 69.75,
    "Guncel Getiri": 558,
    "Net Kar-Zarar (tl)": 278,
    "% Kar- Zarar": 0.9928571428571428,
    "SatisFiyati": "132.4",
    "Satildi mi ?": true
  },
  {
    "": "BORSK",
    "Adet": 16,
    "Alis Fiyati": 26.54,
    "Maliyet (TL)": 424.64,
    "Guncel Fiyat": 28.64,
    "Guncel Getiri": 458.24,
    "Net Kar-Zarar (tl)": 33.60000000000002,
    "% Kar- Zarar": 0.0791258477769405,
    "SatisFiyati": "",
    "Satildi mi ?": false
  },
  {
    "": "MOGAN",
    "Adet": 68,
    "Alis Fiyati": 11.33,
    "Maliyet (TL)": 770.44,
    "Guncel Fiyat": 13.32,
    "Guncel Getiri": 905.76,
    "Net Kar-Zarar (tl)": 135.31999999999994,
    "% Kar- Zarar": 0.17563989408649575,
    "SatisFiyati": "",
    "Satildi mi ?": false
  },
  {
    "": "",
    "Adet": "",
    "Alis Fiyati": "",
    "Maliyet (TL)": "",
    "Guncel Fiyat": "",
    "Guncel Getiri": "",
    "Net Kar-Zarar (tl)": "",
    "% Kar- Zarar": "",
    "SatisFiyati": "",
    "Satildi mi ?": ""
  },
  {
    "": "",
    "Adet": "",
    "Alis Fiyati": "",
    "Maliyet (TL)": "",
    "Guncel Fiyat": "",
    "Guncel Getiri": "",
    "Net Kar-Zarar (tl)": "",
    "% Kar- Zarar": "",
    "SatisFiyati": "",
    "Satildi mi ?": ""
  },
  {
    "": "",
    "Adet": "",
    "Alis Fiyati": "",
    "Maliyet (TL)": "",
    "Guncel Fiyat": "",
    "Guncel Getiri": "",
    "Net Kar-Zarar (tl)": "",
    "% Kar- Zarar": "",
    "SatisFiyati": "",
    "Satildi mi ?": ""
  },
  {
    "": "",
    "Adet": "",
    "Alis Fiyati": "",
    "Maliyet (TL)": "",
    "Guncel Fiyat": "",
    "Guncel Getiri": "",
    "Net Kar-Zarar (tl)": "",
    "% Kar- Zarar": "",
    "SatisFiyati": "",
    "Satildi mi ?": ""
  },
  {
    "": "",
    "Adet": "",
    "Alis Fiyati": "",
    "Maliyet (TL)": "",
    "Guncel Fiyat": "",
    "Guncel Getiri": "",
    "Net Kar-Zarar (tl)": "",
    "% Kar- Zarar": "",
    "SatisFiyati": "",
    "Satildi mi ?": ""
  },
  {
    "": "",
    "Adet": "",
    "Alis Fiyati": "",
    "Maliyet (TL)": "",
    "Guncel Fiyat": "",
    "Guncel Getiri": "",
    "Net Kar-Zarar (tl)": "",
    "% Kar- Zarar": "",
    "SatisFiyati": "",
    "Satildi mi ?": ""
  },
  {
    "": "Toplam",
    "Adet": 0,
    "Alis Fiyati": 0,
    "Maliyet (TL)": 1848.31,
    "Guncel Fiyat": 0,
    "Guncel Getiri": 2176.42,
    "Net Kar-Zarar (tl)": 328.1100000000001,
    "% Kar- Zarar": 0.17751892269153985,
    "SatisFiyati": "",
    "Satildi mi ?": ""
  },
  {
    "": "",
    "Adet": "",
    "Alis Fiyati": "",
    "Maliyet (TL)": "",
    "Guncel Fiyat": "",
    "Guncel Getiri": "",
    "Net Kar-Zarar (tl)": "",
    "% Kar- Zarar": "",
    "SatisFiyati": "",
    "Satildi mi ?": ""
  },
  {
    "": "",
    "Adet": "",
    "Alis Fiyati": "",
    "Maliyet (TL)": "",
    "Guncel Fiyat": "",
    "Guncel Getiri": "",
    "Net Kar-Zarar (tl)": "",
    "% Kar- Zarar": "",
    "SatisFiyati": "",
    "Satildi mi ?": ""
  },
  {
    "": "",
    "Adet": "",
    "Alis Fiyati": "",
    "Maliyet (TL)": "",
    "Guncel Fiyat": "",
    "Guncel Getiri": "",
    "Net Kar-Zarar (tl)": "",
    "% Kar- Zarar": "",
    "SatisFiyati": "",
    "Satildi mi ?": ""
  },
  {
    "": "",
    "Adet": "",
    "Alis Fiyati": "",
    "Maliyet (TL)": "",
    "Guncel Fiyat": "x zx x",
    "Guncel Getiri": "",
    "Net Kar-Zarar (tl)": "",
    "% Kar- Zarar": "",
    "SatisFiyati": "",
    "Satildi mi ?": ""
  },
  {
    "": "",
    "Adet": "",
    "Alis Fiyati": "",
    "Maliyet (TL)": "",
    "Guncel Fiyat": "",
    "Guncel Getiri": "",
    "Net Kar-Zarar (tl)": "",
    "% Kar- Zarar": "",
    "SatisFiyati": "",
    "Satildi mi ?": ""
  },
  {
    "": "",
    "Adet": "",
    "Alis Fiyati": "",
    "Maliyet (TL)": "",
    "Guncel Fiyat": "",
    "Guncel Getiri": "",
    "Net Kar-Zarar (tl)": "",
    "% Kar- Zarar": "",
    "SatisFiyati": "",
    "Satildi mi ?": ""
  },
  {
    "": "",
    "Adet": "",
    "Alis Fiyati": "",
    "Maliyet (TL)": "",
    "Guncel Fiyat": "",
    "Guncel Getiri": "",
    "Net Kar-Zarar (tl)": "",
    "% Kar- Zarar": "",
    "SatisFiyati": "",
    "Satildi mi ?": false
  }
]