[
  {
    "": "",
    "Adet": 75,
    "Alis Fiyati": 5.21,
    "Maliyet (TL)": 390.75,
    "Guncel Fiyat": 7.62,
    "Guncel Getiri": 571.5,
    "Net Kar-Zarar (tl)": 180.75,
    "% Kar- Zarar": 0.4625719769673705,
    "Satildi mi ?": false
  },
  {
    "": "",
    "Adet": 3,
    "Alis Fiyati": 125,
    "Maliyet (TL)": 375,
    "Guncel Fiyat": 243.3,
    "Guncel Getiri": 729.9000000000001,
    "Net Kar-Zarar (tl)": 354.9000000000001,
    "% Kar- Zarar": 0.9464000000000005,
    "Satildi mi ?": false
  },
  {
    "": "",
    "Adet": 14,
    "Alis Fiyati": 10.24,
    "Maliyet (TL)": 143.36,
    "Guncel Fiyat": 16.79,
    "Guncel Getiri": 235.06,
    "Net Kar-Zarar (tl)": 91.69999999999999,
    "% Kar- Zarar": 0.6396484374999997,
    "Satildi mi ?": false
  },
  {
    "": "",
    "Adet": 11,
    "Alis Fiyati": 88.76,
    "Maliyet (TL)": 976.36,
    "Guncel Fiyat": 139.9,
    "Guncel Getiri": 1538.9,
    "Net Kar-Zarar (tl)": 562.5400000000001,
    "% Kar- Zarar": 0.5761604326273099,
    "Satildi mi ?": false
  },
  {
    "": "",
    "Adet": 18,
    "Alis Fiyati": 12.77,
    "Maliyet (TL)": 229.85999999999999,
    "Guncel Fiyat": 22.56,
    "Guncel Getiri": 406.08,
    "Net Kar-Zarar (tl)": 176.22,
    "% Kar- Zarar": 0.7666405638214567,
    "Satildi mi ?": false
  },
  {
    "": "IZENR",
    "Adet": 36,
    "Alis Fiyati": 19,
    "Maliyet (TL)": 684,
    "Guncel Fiyat": 35.44,
    "Guncel Getiri": 1275.84,
    "Net Kar-Zarar (tl)": 591.8399999999999,
    "% Kar- Zarar": 0.8652631578947367,
    "Satildi mi ?": false
  },
  {
    "": "",
    "Adet": 65,
    "Alis Fiyati": 4.3,
    "Maliyet (TL)": 279.5,
    "Guncel Fiyat": 5.72,
    "Guncel Getiri": 371.8,
    "Net Kar-Zarar (tl)": 92.30000000000001,
    "% Kar- Zarar": 0.33023255813953484,
    "Satildi mi ?": false
  },
  {
    "": "",
    "Adet": 46,
    "Alis Fiyati": 9.3,
    "Maliyet (TL)": 427.8,
    "Guncel Fiyat": 26.4,
    "Guncel Getiri": 1214.3999999999999,
    "Net Kar-Zarar (tl)": 786.5999999999999,
    "% Kar- Zarar": 1.8387096774193543,
    "Satildi mi ?": false
  },
  {
    "": "TATEN",
    "Adet": 22,
    "Alis Fiyati": 22.5,
    "Maliyet (TL)": 495,
    "Guncel Fiyat": 39.92,
    "Guncel Getiri": 878.24,
    "Net Kar-Zarar (tl)": 383.24,
    "% Kar- Zarar": 0.7742222222222221,
    "Satildi mi ?": false
  },
  {
    "": "",
    "Adet": 9,
    "Alis Fiyati": 130,
    "Maliyet (TL)": 1170,
    "Guncel Fiyat": 157.9,
    "Guncel Getiri": 1421.1000000000001,
    "Net Kar-Zarar (tl)": 251.10000000000014,
    "% Kar- Zarar": 0.21461538461538468,
    "Satildi mi ?": ""
  },
  {
    "": "",
    "Adet": 10,
    "Alis Fiyati": 15.78,
    "Maliyet (TL)": 157.79999999999998,
    "Guncel Fiyat": 26.4,
    "Guncel Getiri": 264,
    "Net Kar-Zarar (tl)": 106.20000000000002,
    "% Kar- Zarar": 0.673003802281369,
    "Satildi mi ?": ""
  },
  {
    "": "",
    "Adet": 21,
    "Alis Fiyati": 10.97,
    "Maliyet (TL)": 230.37,
    "Guncel Fiyat": 19.46,
    "Guncel Getiri": 408.66,
    "Net Kar-Zarar (tl)": 178.29000000000002,
    "% Kar- Zarar": 0.7739288969917959,
    "Satildi mi ?": ""
  },
  {
    "": "",
    "Adet": 0,
    "Alis Fiyati": 0,
    "Maliyet (TL)": 5559.8,
    "Guncel Fiyat": 0,
    "Guncel Getiri": 9315.48,
    "Net Kar-Zarar (tl)": 3755.6799999999994,
    "% Kar- Zarar": 0.6755063131767329,
    "Satildi mi ?": false
  },
  {
    "": "",
    "Adet": "",
    "Alis Fiyati": "",
    "Maliyet (TL)": "",
    "Guncel Fiyat": "",
    "Guncel Getiri": "",
    "Net Kar-Zarar (tl)": "",
    "% Kar- Zarar": "",
    "Satildi mi ?": ""
  },
  {
    "": "",
    "Adet": "",
    "Alis Fiyati": "",
    "Maliyet (TL)": "",
    "Guncel Fiyat": "",
    "Guncel Getiri": "",
    "Net Kar-Zarar (tl)": "",
    "% Kar- Zarar": "",
    "Satildi mi ?": ""
  },
  {
    "": "",
    "Adet": "",
    "Alis Fiyati": "",
    "Maliyet (TL)": "",
    "Guncel Fiyat": "",
    "Guncel Getiri": "",
    "Net Kar-Zarar (tl)": "",
    "% Kar- Zarar": "",
    "Satildi mi ?": ""
  },
  {
    "": "",
    "Adet": "",
    "Alis Fiyati": "",
    "Maliyet (TL)": "",
    "Guncel Fiyat": "",
    "Guncel Getiri": "",
    "Net Kar-Zarar (tl)": "",
    "% Kar- Zarar": "",
    "Satildi mi ?": ""
  },
  {
    "": "",
    "Adet": "",
    "Alis Fiyati": "",
    "Maliyet (TL)": "",
    "Guncel Fiyat": "",
    "Guncel Getiri": "",
    "Net Kar-Zarar (tl)": "",
    "% Kar- Zarar": "",
    "Satildi mi ?": ""
  },
  {
    "": "",
    "Adet": "",
    "Alis Fiyati": "",
    "Maliyet (TL)": "",
    "Guncel Fiyat": "",
    "Guncel Getiri": "",
    "Net Kar-Zarar (tl)": "",
    "% Kar- Zarar": "",
    "Satildi mi ?": ""
  },
  {
    "": "",
    "Adet": "",
    "Alis Fiyati": "",
    "Maliyet (TL)": "",
    "Guncel Fiyat": "",
    "Guncel Getiri": "",
    "Net Kar-Zarar (tl)": "",
    "% Kar- Zarar": "",
    "Satildi mi ?": false
  }
]