[
  {
    "": "",
    "Adet": 75,
    "Alis Fiyati": 5.21,
    "Maliyet (TL)": 390.75,
    "Guncel Fiyat": 35.78,
    "Guncel Getiri": 2683.5,
    "Net Kar-Zarar (tl)": 2292.75,
    "% Kar- Zarar": 5.867562380038388,
    "Satildi mi ?": false
  },
  {
    "": "",
    "Adet": 3,
    "Alis Fiyati": 125,
    "Maliyet (TL)": 375,
    "Guncel Fiyat": 655.5,
    "Guncel Getiri": 1966.5,
    "Net Kar-Zarar (tl)": 1591.5,
    "% Kar- Zarar": 4.244,
    "Satildi mi ?": false
  },
  {
    "": "",
    "Adet": 14,
    "Alis Fiyati": 10.24,
    "Maliyet (TL)": 143.36,
    "Guncel Fiyat": 17.74,
    "Guncel Getiri": 248.35999999999999,
    "Net Kar-Zarar (tl)": 104.99999999999997,
    "% Kar- Zarar": 0.7324218749999997,
    "Satildi mi ?": false
  },
  {
    "": "",
    "Adet": 11,
    "Alis Fiyati": 88.76,
    "Maliyet (TL)": 976.36,
    "Guncel Fiyat": 153.7,
    "Guncel Getiri": 1690.6999999999998,
    "Net Kar-Zarar (tl)": 714.3399999999998,
    "% Kar- Zarar": 0.7316358720144208,
    "Satildi mi ?": false
  },
  {
    "": "",
    "Adet": 18,
    "Alis Fiyati": 12.77,
    "Maliyet (TL)": 229.85999999999999,
    "Guncel Fiyat": 66.9,
    "Guncel Getiri": 1204.2,
    "Net Kar-Zarar (tl)": 974.34,
    "% Kar- Zarar": 4.23884103367267,
    "Satildi mi ?": false
  },
  {
    "": "IZENR",
    "Adet": 36,
    "Alis Fiyati": 19,
    "Maliyet (TL)": 684,
    "Guncel Fiyat": 34.92,
    "Guncel Getiri": 1257.1200000000001,
    "Net Kar-Zarar (tl)": 573.1200000000001,
    "% Kar- Zarar": 0.8378947368421055,
    "Satildi mi ?": false
  },
  {
    "": "",
    "Adet": 65,
    "Alis Fiyati": 4.3,
    "Maliyet (TL)": 279.5,
    "Guncel Fiyat": 6.22,
    "Guncel Getiri": 404.3,
    "Net Kar-Zarar (tl)": 124.80000000000001,
    "% Kar- Zarar": 0.4465116279069767,
    "Satildi mi ?": false
  },
  {
    "": "",
    "Adet": 46,
    "Alis Fiyati": 9.3,
    "Maliyet (TL)": 427.8,
    "Guncel Fiyat": 42.28,
    "Guncel Getiri": 1944.88,
    "Net Kar-Zarar (tl)": 1517.0800000000002,
    "% Kar- Zarar": 3.546236559139784,
    "Satildi mi ?": false
  },
  {
    "": "TATEN",
    "Adet": 22,
    "Alis Fiyati": 22.5,
    "Maliyet (TL)": 495,
    "Guncel Fiyat": 44.78,
    "Guncel Getiri": 985.1600000000001,
    "Net Kar-Zarar (tl)": 490.1600000000001,
    "% Kar- Zarar": 0.9902222222222224,
    "Satildi mi ?": false
  },
  {
    "": "",
    "Adet": 9,
    "Alis Fiyati": 130,
    "Maliyet (TL)": 1170,
    "Guncel Fiyat": 142.6,
    "Guncel Getiri": 1283.3999999999999,
    "Net Kar-Zarar (tl)": 113.39999999999986,
    "% Kar- Zarar": 0.09692307692307693,
    "Satildi mi ?": ""
  },
  {
    "": "",
    "Adet": 10,
    "Alis Fiyati": 15.78,
    "Maliyet (TL)": 157.79999999999998,
    "Guncel Fiyat": 32.34,
    "Guncel Getiri": 323.40000000000003,
    "Net Kar-Zarar (tl)": 165.60000000000005,
    "% Kar- Zarar": 1.0494296577946773,
    "Satildi mi ?": ""
  },
  {
    "": "",
    "Adet": 21,
    "Alis Fiyati": 10.97,
    "Maliyet (TL)": 230.37,
    "Guncel Fiyat": 20.5,
    "Guncel Getiri": 430.5,
    "Net Kar-Zarar (tl)": 200.13,
    "% Kar- Zarar": 0.8687329079307199,
    "Satildi mi ?": ""
  },
  {
    "": "",
    "Adet": 0,
    "Alis Fiyati": 0,
    "Maliyet (TL)": 5559.8,
    "Guncel Fiyat": 0,
    "Guncel Getiri": 14422.019999999997,
    "Net Kar-Zarar (tl)": 8862.219999999998,
    "% Kar- Zarar": 1.593981797906399,
    "Satildi mi ?": false
  },
  {
    "": "",
    "Adet": "",
    "Alis Fiyati": "",
    "Maliyet (TL)": "",
    "Guncel Fiyat": "",
    "Guncel Getiri": "",
    "Net Kar-Zarar (tl)": "",
    "% Kar- Zarar": "",
    "Satildi mi ?": ""
  },
  {
    "": "",
    "Adet": "",
    "Alis Fiyati": "",
    "Maliyet (TL)": "",
    "Guncel Fiyat": "",
    "Guncel Getiri": "",
    "Net Kar-Zarar (tl)": "",
    "% Kar- Zarar": "",
    "Satildi mi ?": ""
  },
  {
    "": "",
    "Adet": "",
    "Alis Fiyati": "",
    "Maliyet (TL)": "",
    "Guncel Fiyat": "",
    "Guncel Getiri": "",
    "Net Kar-Zarar (tl)": "",
    "% Kar- Zarar": "",
    "Satildi mi ?": ""
  },
  {
    "": "",
    "Adet": "",
    "Alis Fiyati": "",
    "Maliyet (TL)": "",
    "Guncel Fiyat": "",
    "Guncel Getiri": "",
    "Net Kar-Zarar (tl)": "",
    "% Kar- Zarar": "",
    "Satildi mi ?": ""
  },
  {
    "": "",
    "Adet": "",
    "Alis Fiyati": "",
    "Maliyet (TL)": "",
    "Guncel Fiyat": "",
    "Guncel Getiri": "",
    "Net Kar-Zarar (tl)": "",
    "% Kar- Zarar": "",
    "Satildi mi ?": ""
  },
  {
    "": "",
    "Adet": "",
    "Alis Fiyati": "",
    "Maliyet (TL)": "",
    "Guncel Fiyat": "",
    "Guncel Getiri": "",
    "Net Kar-Zarar (tl)": "",
    "% Kar- Zarar": "",
    "Satildi mi ?": ""
  },
  {
    "": "",
    "Adet": "",
    "Alis Fiyati": "",
    "Maliyet (TL)": "",
    "Guncel Fiyat": "",
    "Guncel Getiri": "",
    "Net Kar-Zarar (tl)": "",
    "% Kar- Zarar": "",
    "Satildi mi ?": false
  }
]