[
  {
    "": "",
    "Adet": 75,
    "Alis Fiyati": 5.21,
    "Maliyet (TL)": 390.75,
    "Guncel Fiyat": 11.43,
    "Guncel Getiri": 857.25,
    "Net Kar-Zarar (tl)": 466.5,
    "% Kar- Zarar": 1.1938579654510557,
    "Satildi mi ?": false
  },
  {
    "": "",
    "Adet": 3,
    "Alis Fiyati": 125,
    "Maliyet (TL)": 375,
    "Guncel Fiyat": 333,
    "Guncel Getiri": 999,
    "Net Kar-Zarar (tl)": 624,
    "% Kar- Zarar": 1.6640000000000004,
    "Satildi mi ?": false
  },
  {
    "": "",
    "Adet": 14,
    "Alis Fiyati": 10.24,
    "Maliyet (TL)": 143.36,
    "Guncel Fiyat": 10.9,
    "Guncel Getiri": 152.6,
    "Net Kar-Zarar (tl)": 9.23999999999998,
    "% Kar- Zarar": 0.06445312499999972,
    "Satildi mi ?": false
  },
  {
    "": "",
    "Adet": 11,
    "Alis Fiyati": 88.76,
    "Maliyet (TL)": 976.36,
    "Guncel Fiyat": 111.3,
    "Guncel Getiri": 1224.3,
    "Net Kar-Zarar (tl)": 247.93999999999994,
    "% Kar- Zarar": 0.2539432176656152,
    "Satildi mi ?": false
  },
  {
    "": "",
    "Adet": 18,
    "Alis Fiyati": 12.77,
    "Maliyet (TL)": 229.85999999999999,
    "Guncel Fiyat": 46.46,
    "Guncel Getiri": 836.28,
    "Net Kar-Zarar (tl)": 606.42,
    "% Kar- Zarar": 2.6382145653876274,
    "Satildi mi ?": false
  },
  {
    "": "IZENR",
    "Adet": 36,
    "Alis Fiyati": 19,
    "Maliyet (TL)": 684,
    "Guncel Fiyat": 26.8,
    "Guncel Getiri": 964.8000000000001,
    "Net Kar-Zarar (tl)": 280.80000000000007,
    "% Kar- Zarar": 0.41052631578947396,
    "Satildi mi ?": false
  },
  {
    "": "",
    "Adet": 65,
    "Alis Fiyati": 4.3,
    "Maliyet (TL)": 279.5,
    "Guncel Fiyat": 4.88,
    "Guncel Getiri": 317.2,
    "Net Kar-Zarar (tl)": 37.69999999999999,
    "% Kar- Zarar": 0.13488372093023243,
    "Satildi mi ?": false
  },
  {
    "": "",
    "Adet": 46,
    "Alis Fiyati": 9.3,
    "Maliyet (TL)": 427.8,
    "Guncel Fiyat": 21.98,
    "Guncel Getiri": 1011.08,
    "Net Kar-Zarar (tl)": 583.28,
    "% Kar- Zarar": 1.3634408602150534,
    "Satildi mi ?": false
  },
  {
    "": "TATEN",
    "Adet": 22,
    "Alis Fiyati": 22.5,
    "Maliyet (TL)": 495,
    "Guncel Fiyat": 29.9,
    "Guncel Getiri": 657.8,
    "Net Kar-Zarar (tl)": 162.79999999999995,
    "% Kar- Zarar": 0.32888888888888884,
    "Satildi mi ?": false
  },
  {
    "": "",
    "Adet": 9,
    "Alis Fiyati": 130,
    "Maliyet (TL)": 1170,
    "Guncel Fiyat": 113.4,
    "Guncel Getiri": 1020.6,
    "Net Kar-Zarar (tl)": -149.39999999999998,
    "% Kar- Zarar": -0.1276923076923076,
    "Satildi mi ?": ""
  },
  {
    "": "",
    "Adet": 10,
    "Alis Fiyati": 15.78,
    "Maliyet (TL)": 157.79999999999998,
    "Guncel Fiyat": 23.3,
    "Guncel Getiri": 233,
    "Net Kar-Zarar (tl)": 75.20000000000002,
    "% Kar- Zarar": 0.47655259822560225,
    "Satildi mi ?": ""
  },
  {
    "": "",
    "Adet": 21,
    "Alis Fiyati": 10.97,
    "Maliyet (TL)": 230.37,
    "Guncel Fiyat": 13.79,
    "Guncel Getiri": 289.59,
    "Net Kar-Zarar (tl)": 59.21999999999997,
    "% Kar- Zarar": 0.2570647219690063,
    "Satildi mi ?": ""
  },
  {
    "": "",
    "Adet": 0,
    "Alis Fiyati": 0,
    "Maliyet (TL)": 5559.8,
    "Guncel Fiyat": 0,
    "Guncel Getiri": 8563.5,
    "Net Kar-Zarar (tl)": 3003.7,
    "% Kar- Zarar": 0.5402532465196589,
    "Satildi mi ?": false
  },
  {
    "": "",
    "Adet": "",
    "Alis Fiyati": "",
    "Maliyet (TL)": "",
    "Guncel Fiyat": "",
    "Guncel Getiri": "",
    "Net Kar-Zarar (tl)": "",
    "% Kar- Zarar": "",
    "Satildi mi ?": ""
  },
  {
    "": "",
    "Adet": "",
    "Alis Fiyati": "",
    "Maliyet (TL)": "",
    "Guncel Fiyat": "",
    "Guncel Getiri": "",
    "Net Kar-Zarar (tl)": "",
    "% Kar- Zarar": "",
    "Satildi mi ?": ""
  },
  {
    "": "",
    "Adet": "",
    "Alis Fiyati": "",
    "Maliyet (TL)": "",
    "Guncel Fiyat": "",
    "Guncel Getiri": "",
    "Net Kar-Zarar (tl)": "",
    "% Kar- Zarar": "",
    "Satildi mi ?": ""
  },
  {
    "": "",
    "Adet": "",
    "Alis Fiyati": "",
    "Maliyet (TL)": "",
    "Guncel Fiyat": "",
    "Guncel Getiri": "",
    "Net Kar-Zarar (tl)": "",
    "% Kar- Zarar": "",
    "Satildi mi ?": ""
  },
  {
    "": "",
    "Adet": "",
    "Alis Fiyati": "",
    "Maliyet (TL)": "",
    "Guncel Fiyat": "",
    "Guncel Getiri": "",
    "Net Kar-Zarar (tl)": "",
    "% Kar- Zarar": "",
    "Satildi mi ?": ""
  },
  {
    "": "",
    "Adet": "",
    "Alis Fiyati": "",
    "Maliyet (TL)": "",
    "Guncel Fiyat": "",
    "Guncel Getiri": "",
    "Net Kar-Zarar (tl)": "",
    "% Kar- Zarar": "",
    "Satildi mi ?": ""
  },
  {
    "": "",
    "Adet": "",
    "Alis Fiyati": "",
    "Maliyet (TL)": "",
    "Guncel Fiyat": "",
    "Guncel Getiri": "",
    "Net Kar-Zarar (tl)": "",
    "% Kar- Zarar": "",
    "Satildi mi ?": false
  }
]