[
  {
    "": "",
    "Adet": 75,
    "Alis Fiyati": 5.21,
    "Maliyet (TL)": 390.75,
    "Guncel Fiyat": 42.62,
    "Guncel Getiri": 3196.5,
    "Net Kar-Zarar (tl)": 2805.75,
    "% Kar- Zarar": 7.18042226487524,
    "Satildi mi ?": false
  },
  {
    "": "",
    "Adet": 3,
    "Alis Fiyati": 125,
    "Maliyet (TL)": 375,
    "Guncel Fiyat": 636.5,
    "Guncel Getiri": 1909.5,
    "Net Kar-Zarar (tl)": 1534.5,
    "% Kar- Zarar": 4.092,
    "Satildi mi ?": false
  },
  {
    "": "",
    "Adet": 14,
    "Alis Fiyati": 10.24,
    "Maliyet (TL)": 143.36,
    "Guncel Fiyat": 18.4,
    "Guncel Getiri": 257.59999999999997,
    "Net Kar-Zarar (tl)": 114.23999999999995,
    "% Kar- Zarar": 0.7968749999999994,
    "Satildi mi ?": false
  },
  {
    "": "",
    "Adet": 11,
    "Alis Fiyati": 88.76,
    "Maliyet (TL)": 976.36,
    "Guncel Fiyat": 152.8,
    "Guncel Getiri": 1680.8000000000002,
    "Net Kar-Zarar (tl)": 704.4400000000002,
    "% Kar- Zarar": 0.7214961694456966,
    "Satildi mi ?": false
  },
  {
    "": "",
    "Adet": 18,
    "Alis Fiyati": 12.77,
    "Maliyet (TL)": 229.85999999999999,
    "Guncel Fiyat": 66.2,
    "Guncel Getiri": 1191.6000000000001,
    "Net Kar-Zarar (tl)": 961.7400000000001,
    "% Kar- Zarar": 4.184025058731403,
    "Satildi mi ?": false
  },
  {
    "": "IZENR",
    "Adet": 36,
    "Alis Fiyati": 19,
    "Maliyet (TL)": 684,
    "Guncel Fiyat": 34.14,
    "Guncel Getiri": 1229.04,
    "Net Kar-Zarar (tl)": 545.04,
    "% Kar- Zarar": 0.7968421052631578,
    "Satildi mi ?": false
  },
  {
    "": "",
    "Adet": 65,
    "Alis Fiyati": 4.3,
    "Maliyet (TL)": 279.5,
    "Guncel Fiyat": 6.19,
    "Guncel Getiri": 402.35,
    "Net Kar-Zarar (tl)": 122.85000000000002,
    "% Kar- Zarar": 0.43953488372093036,
    "Satildi mi ?": false
  },
  {
    "": "",
    "Adet": 46,
    "Alis Fiyati": 9.3,
    "Maliyet (TL)": 427.8,
    "Guncel Fiyat": 49.1,
    "Guncel Getiri": 2258.6,
    "Net Kar-Zarar (tl)": 1830.8,
    "% Kar- Zarar": 4.279569892473117,
    "Satildi mi ?": false
  },
  {
    "": "TATEN",
    "Adet": 22,
    "Alis Fiyati": 22.5,
    "Maliyet (TL)": 495,
    "Guncel Fiyat": 44.92,
    "Guncel Getiri": 988.24,
    "Net Kar-Zarar (tl)": 493.24,
    "% Kar- Zarar": 0.9964444444444445,
    "Satildi mi ?": false
  },
  {
    "": "",
    "Adet": 9,
    "Alis Fiyati": 130,
    "Maliyet (TL)": 1170,
    "Guncel Fiyat": 150.5,
    "Guncel Getiri": 1354.5,
    "Net Kar-Zarar (tl)": 184.5,
    "% Kar- Zarar": 0.15769230769230774,
    "Satildi mi ?": ""
  },
  {
    "": "",
    "Adet": 10,
    "Alis Fiyati": 15.78,
    "Maliyet (TL)": 157.79999999999998,
    "Guncel Fiyat": 36.48,
    "Guncel Getiri": 364.79999999999995,
    "Net Kar-Zarar (tl)": 206.99999999999997,
    "% Kar- Zarar": 1.3117870722433458,
    "Satildi mi ?": ""
  },
  {
    "": "",
    "Adet": 21,
    "Alis Fiyati": 10.97,
    "Maliyet (TL)": 230.37,
    "Guncel Fiyat": 26.64,
    "Guncel Getiri": 559.44,
    "Net Kar-Zarar (tl)": 329.07000000000005,
    "% Kar- Zarar": 1.4284412032816776,
    "Satildi mi ?": ""
  },
  {
    "": "",
    "Adet": 0,
    "Alis Fiyati": 0,
    "Maliyet (TL)": 5559.8,
    "Guncel Fiyat": 0,
    "Guncel Getiri": 15392.970000000001,
    "Net Kar-Zarar (tl)": 9833.170000000002,
    "% Kar- Zarar": 1.7686193747976546,
    "Satildi mi ?": false
  },
  {
    "": "",
    "Adet": "",
    "Alis Fiyati": "",
    "Maliyet (TL)": "",
    "Guncel Fiyat": "",
    "Guncel Getiri": "",
    "Net Kar-Zarar (tl)": "",
    "% Kar- Zarar": "",
    "Satildi mi ?": ""
  },
  {
    "": "",
    "Adet": "",
    "Alis Fiyati": "",
    "Maliyet (TL)": "",
    "Guncel Fiyat": "",
    "Guncel Getiri": "",
    "Net Kar-Zarar (tl)": "",
    "% Kar- Zarar": "",
    "Satildi mi ?": ""
  },
  {
    "": "",
    "Adet": "",
    "Alis Fiyati": "",
    "Maliyet (TL)": "",
    "Guncel Fiyat": "",
    "Guncel Getiri": "",
    "Net Kar-Zarar (tl)": "",
    "% Kar- Zarar": "",
    "Satildi mi ?": ""
  },
  {
    "": "",
    "Adet": "",
    "Alis Fiyati": "",
    "Maliyet (TL)": "",
    "Guncel Fiyat": "",
    "Guncel Getiri": "",
    "Net Kar-Zarar (tl)": "",
    "% Kar- Zarar": "",
    "Satildi mi ?": ""
  },
  {
    "": "",
    "Adet": "",
    "Alis Fiyati": "",
    "Maliyet (TL)": "",
    "Guncel Fiyat": "",
    "Guncel Getiri": "",
    "Net Kar-Zarar (tl)": "",
    "% Kar- Zarar": "",
    "Satildi mi ?": ""
  },
  {
    "": "",
    "Adet": "",
    "Alis Fiyati": "",
    "Maliyet (TL)": "",
    "Guncel Fiyat": "",
    "Guncel Getiri": "",
    "Net Kar-Zarar (tl)": "",
    "% Kar- Zarar": "",
    "Satildi mi ?": ""
  },
  {
    "": "",
    "Adet": "",
    "Alis Fiyati": "",
    "Maliyet (TL)": "",
    "Guncel Fiyat": "",
    "Guncel Getiri": "",
    "Net Kar-Zarar (tl)": "",
    "% Kar- Zarar": "",
    "Satildi mi ?": false
  }
]