[
  {
    "": "DMRGD",
    "Adet": 14,
    "Alis Fiyati": 10.24,
    "Maliyet (TL)": 143.36,
    "Guncel Fiyat": 15.73,
    "Guncel Getiri": 220.22,
    "Net Kar-Zarar (tl)": 76.85999999999999,
    "% Kar- Zarar": 0.5361328124999997,
    "SatisFiyati": "",
    "Satildi mi ?": false
  },
  {
    "": "MHRGY",
    "Adet": 65,
    "Alis Fiyati": 4.3,
    "Maliyet (TL)": 279.5,
    "Guncel Fiyat": 5.01,
    "Guncel Getiri": 325.65,
    "Net Kar-Zarar (tl)": 46.14999999999998,
    "% Kar- Zarar": 0.16511627906976728,
    "SatisFiyati": "",
    "Satildi mi ?": false
  },
  {
    "": "MARBL",
    "Adet": 21,
    "Alis Fiyati": 10.97,
    "Maliyet (TL)": 230.37,
    "Guncel Fiyat": 18.83,
    "Guncel Getiri": 395.42999999999995,
    "Net Kar-Zarar (tl)": 165.05999999999995,
    "% Kar- Zarar": 0.7164995442114858,
    "SatisFiyati": "",
    "Satildi mi ?": false
  },
  {
    "": "PATEK",
    "Adet": 8,
    "Alis Fiyati": 35,
    "Maliyet (TL)": 280,
    "Guncel Fiyat": 111.8,
    "Guncel Getiri": 894.4,
    "Net Kar-Zarar (tl)": 614.4,
    "% Kar- Zarar": 2.1942857142857144,
    "SatisFiyati": "132.4",
    "Satildi mi ?": true
  },
  {
    "": "BORSK",
    "Adet": 16,
    "Alis Fiyati": 26.54,
    "Maliyet (TL)": 424.64,
    "Guncel Fiyat": 35.76,
    "Guncel Getiri": 572.16,
    "Net Kar-Zarar (tl)": 147.51999999999998,
    "% Kar- Zarar": 0.3474001507159005,
    "SatisFiyati": "",
    "Satildi mi ?": false
  },
  {
    "": "MOGAN",
    "Adet": 68,
    "Alis Fiyati": 11.33,
    "Maliyet (TL)": 770.44,
    "Guncel Fiyat": 16.47,
    "Guncel Getiri": 1119.96,
    "Net Kar-Zarar (tl)": 349.52,
    "% Kar- Zarar": 0.45366284201235657,
    "SatisFiyati": "",
    "Satildi mi ?": false
  },
  {
    "": "",
    "Adet": "",
    "Alis Fiyati": "",
    "Maliyet (TL)": "",
    "Guncel Fiyat": "",
    "Guncel Getiri": "",
    "Net Kar-Zarar (tl)": "",
    "% Kar- Zarar": "",
    "SatisFiyati": "",
    "Satildi mi ?": ""
  },
  {
    "": "",
    "Adet": "",
    "Alis Fiyati": "",
    "Maliyet (TL)": "",
    "Guncel Fiyat": "",
    "Guncel Getiri": "",
    "Net Kar-Zarar (tl)": "",
    "% Kar- Zarar": "",
    "SatisFiyati": "",
    "Satildi mi ?": ""
  },
  {
    "": "",
    "Adet": "",
    "Alis Fiyati": "",
    "Maliyet (TL)": "",
    "Guncel Fiyat": "",
    "Guncel Getiri": "",
    "Net Kar-Zarar (tl)": "",
    "% Kar- Zarar": "",
    "SatisFiyati": "",
    "Satildi mi ?": ""
  },
  {
    "": "",
    "Adet": "",
    "Alis Fiyati": "",
    "Maliyet (TL)": "",
    "Guncel Fiyat": "",
    "Guncel Getiri": "",
    "Net Kar-Zarar (tl)": "",
    "% Kar- Zarar": "",
    "SatisFiyati": "",
    "Satildi mi ?": ""
  },
  {
    "": "",
    "Adet": "",
    "Alis Fiyati": "",
    "Maliyet (TL)": "",
    "Guncel Fiyat": "",
    "Guncel Getiri": "",
    "Net Kar-Zarar (tl)": "",
    "% Kar- Zarar": "",
    "SatisFiyati": "",
    "Satildi mi ?": ""
  },
  {
    "": "",
    "Adet": "",
    "Alis Fiyati": "",
    "Maliyet (TL)": "",
    "Guncel Fiyat": "",
    "Guncel Getiri": "",
    "Net Kar-Zarar (tl)": "",
    "% Kar- Zarar": "",
    "SatisFiyati": "",
    "Satildi mi ?": ""
  },
  {
    "": "Toplam",
    "Adet": 0,
    "Alis Fiyati": 0,
    "Maliyet (TL)": 1848.31,
    "Guncel Fiyat": 0,
    "Guncel Getiri": 2633.42,
    "Net Kar-Zarar (tl)": 785.1100000000001,
    "% Kar- Zarar": 0.4247718185802165,
    "SatisFiyati": "",
    "Satildi mi ?": ""
  },
  {
    "": "",
    "Adet": "",
    "Alis Fiyati": "",
    "Maliyet (TL)": "",
    "Guncel Fiyat": "",
    "Guncel Getiri": "",
    "Net Kar-Zarar (tl)": "",
    "% Kar- Zarar": "",
    "SatisFiyati": "",
    "Satildi mi ?": ""
  },
  {
    "": "",
    "Adet": "",
    "Alis Fiyati": "",
    "Maliyet (TL)": "",
    "Guncel Fiyat": "",
    "Guncel Getiri": "",
    "Net Kar-Zarar (tl)": "",
    "% Kar- Zarar": "",
    "SatisFiyati": "",
    "Satildi mi ?": ""
  },
  {
    "": "",
    "Adet": "",
    "Alis Fiyati": "",
    "Maliyet (TL)": "",
    "Guncel Fiyat": "",
    "Guncel Getiri": "",
    "Net Kar-Zarar (tl)": "",
    "% Kar- Zarar": "",
    "SatisFiyati": "",
    "Satildi mi ?": ""
  },
  {
    "": "",
    "Adet": "",
    "Alis Fiyati": "",
    "Maliyet (TL)": "",
    "Guncel Fiyat": "x zx x",
    "Guncel Getiri": "",
    "Net Kar-Zarar (tl)": "",
    "% Kar- Zarar": "",
    "SatisFiyati": "",
    "Satildi mi ?": ""
  },
  {
    "": "",
    "Adet": "",
    "Alis Fiyati": "",
    "Maliyet (TL)": "",
    "Guncel Fiyat": "",
    "Guncel Getiri": "",
    "Net Kar-Zarar (tl)": "",
    "% Kar- Zarar": "",
    "SatisFiyati": "",
    "Satildi mi ?": ""
  },
  {
    "": "",
    "Adet": "",
    "Alis Fiyati": "",
    "Maliyet (TL)": "",
    "Guncel Fiyat": "",
    "Guncel Getiri": "",
    "Net Kar-Zarar (tl)": "",
    "% Kar- Zarar": "",
    "SatisFiyati": "",
    "Satildi mi ?": ""
  },
  {
    "": "",
    "Adet": "",
    "Alis Fiyati": "",
    "Maliyet (TL)": "",
    "Guncel Fiyat": "",
    "Guncel Getiri": "",
    "Net Kar-Zarar (tl)": "",
    "% Kar- Zarar": "",
    "SatisFiyati": "",
    "Satildi mi ?": false
  }
]