[
  {
    "Adi": "BYDNR",
    "Adet": 14,
    "Alis Fiyati": 21,
    "Maliyet (TL)": 294,
    "Guncel Fiyat": 42.78,
    "Guncel Getiri": 598.9200000000001,
    "Net Kar-Zarar (tl)": 304.9200000000001,
    "% Kar- Zarar": 1.0371428571428571,
    "": "BYDNR",
    "Satildi mi ?": false
  },
  {
    "Adi": "ENERY",
    "Adet": 11,
    "Alis Fiyati": 88.76,
    "Maliyet (TL)": 976.36,
    "Guncel Fiyat": 162.5,
    "Guncel Getiri": 1787.5,
    "Net Kar-Zarar (tl)": 811.14,
    "% Kar- Zarar": 0.8307796304641729,
    "": "ENERY",
    "Satildi mi ?": false
  },
  {
    "Adi": "IZENR",
    "Adet": 36,
    "Alis Fiyati": 19,
    "Maliyet (TL)": 684,
    "Guncel Fiyat": 53.6,
    "Guncel Getiri": 1929.6000000000001,
    "Net Kar-Zarar (tl)": 1245.6000000000001,
    "% Kar- Zarar": 1.821052631578948,
    "": "IZENR",
    "Satildi mi ?": false
  },
  {
    "Adi": "KZGYO",
    "Adet": 14,
    "Alis Fiyati": 20.76,
    "Maliyet (TL)": 290.64000000000004,
    "Guncel Fiyat": 31.14,
    "Guncel Getiri": 435.96000000000004,
    "Net Kar-Zarar (tl)": 145.32,
    "% Kar- Zarar": 0.5,
    "": "KZGYO",
    "Satildi mi ?": false
  },
  {
    "Adi": "TATEN",
    "Adet": 22,
    "Alis Fiyati": 22.5,
    "Maliyet (TL)": 495,
    "Guncel Fiyat": 51.15,
    "Guncel Getiri": 1125.3,
    "Net Kar-Zarar (tl)": 630.3,
    "% Kar- Zarar": 1.2733333333333334,
    "": "TATEN",
    "Satildi mi ?": false
  },
  {
    "Adi": "EBEBK",
    "Adet": 5,
    "Alis Fiyati": 46.5,
    "Maliyet (TL)": 232.5,
    "Guncel Fiyat": 68.7,
    "Guncel Getiri": 343.5,
    "Net Kar-Zarar (tl)": 111,
    "% Kar- Zarar": 0.47741935483870973,
    "": "EBEBK",
    "Satildi mi ?": false
  },
  {
    "Adi": "TARKM",
    "Adet": 1,
    "Alis Fiyati": 107.5,
    "Maliyet (TL)": 107.5,
    "Guncel Fiyat": 336.9,
    "Guncel Getiri": 336.9,
    "Net Kar-Zarar (tl)": 229.39999999999998,
    "% Kar- Zarar": 2.1339534883720934,
    "": "TARKM",
    "Satildi mi ?": false
  },
  {
    "Adi": "GIPTA",
    "Adet": 9,
    "Alis Fiyati": 20.9,
    "Maliyet (TL)": 188.1,
    "Guncel Fiyat": 33.24,
    "Guncel Getiri": 299.16,
    "Net Kar-Zarar (tl)": 111.06000000000003,
    "% Kar- Zarar": 0.5904306220095696,
    "": "",
    "Satildi mi ?": false
  },
  {
    "Adi": "REEDR",
    "Adet": 46,
    "Alis Fiyati": 9.3,
    "Maliyet (TL)": 427.8,
    "Guncel Fiyat": 14.96,
    "Guncel Getiri": 688.1600000000001,
    "Net Kar-Zarar (tl)": 260.36000000000007,
    "% Kar- Zarar": 0.6086021505376346,
    "": "",
    "Satildi mi ?": false
  },
  {
    "Adi": "HATSN",
    "Adet": 9,
    "Alis Fiyati": 22.6,
    "Maliyet (TL)": 203.4,
    "Guncel Fiyat": 33.06,
    "Guncel Getiri": 297.54,
    "Net Kar-Zarar (tl)": 94.14000000000001,
    "% Kar- Zarar": 0.46283185840707974,
    "": "",
    "Satildi mi ?": false
  },
  {
    "Adi": "Toplam",
    "Adet": 0,
    "Alis Fiyati": 0,
    "Maliyet (TL)": 3899.3,
    "Guncel Fiyat": 0,
    "Guncel Getiri": 7842.54,
    "Net Kar-Zarar (tl)": 3943.24,
    "% Kar- Zarar": 1.0112686892519167,
    "": "",
    "Satildi mi ?": false
  }
]