[
  {
    "": "DMRGD",
    "Adet": 14,
    "Alis Fiyati": 10.24,
    "Maliyet (TL)": 143.36,
    "Guncel Fiyat": 16.07,
    "Guncel Getiri": 224.98000000000002,
    "Net Kar-Zarar (tl)": 81.62,
    "% Kar- Zarar": 0.5693359375,
    "SatisFiyati": "",
    "Satildi mi ?": false
  },
  {
    "": "MHRGY",
    "Adet": 65,
    "Alis Fiyati": 4.3,
    "Maliyet (TL)": 279.5,
    "Guncel Fiyat": 4.92,
    "Guncel Getiri": 319.8,
    "Net Kar-Zarar (tl)": 40.30000000000001,
    "% Kar- Zarar": 0.14418604651162809,
    "SatisFiyati": "",
    "Satildi mi ?": false
  },
  {
    "": "MARBL",
    "Adet": 21,
    "Alis Fiyati": 10.97,
    "Maliyet (TL)": 230.37,
    "Guncel Fiyat": 18.7,
    "Guncel Getiri": 392.7,
    "Net Kar-Zarar (tl)": 162.32999999999998,
    "% Kar- Zarar": 0.7046490428441203,
    "SatisFiyati": "",
    "Satildi mi ?": false
  },
  {
    "": "PATEK",
    "Adet": 8,
    "Alis Fiyati": 35,
    "Maliyet (TL)": 280,
    "Guncel Fiyat": 106,
    "Guncel Getiri": 848,
    "Net Kar-Zarar (tl)": 568,
    "% Kar- Zarar": 2.0285714285714285,
    "SatisFiyati": "132.4",
    "Satildi mi ?": true
  },
  {
    "": "BORSK",
    "Adet": 16,
    "Alis Fiyati": 26.54,
    "Maliyet (TL)": 424.64,
    "Guncel Fiyat": 35.14,
    "Guncel Getiri": 562.24,
    "Net Kar-Zarar (tl)": 137.60000000000002,
    "% Kar- Zarar": 0.32403918613413707,
    "SatisFiyati": "",
    "Satildi mi ?": false
  },
  {
    "": "MOGAN",
    "Adet": 68,
    "Alis Fiyati": 11.33,
    "Maliyet (TL)": 770.44,
    "Guncel Fiyat": 16.32,
    "Guncel Getiri": 1109.76,
    "Net Kar-Zarar (tl)": 339.31999999999994,
    "% Kar- Zarar": 0.4404236540158871,
    "SatisFiyati": "",
    "Satildi mi ?": false
  },
  {
    "": "",
    "Adet": "",
    "Alis Fiyati": "",
    "Maliyet (TL)": "",
    "Guncel Fiyat": "",
    "Guncel Getiri": "",
    "Net Kar-Zarar (tl)": "",
    "% Kar- Zarar": "",
    "SatisFiyati": "",
    "Satildi mi ?": ""
  },
  {
    "": "",
    "Adet": "",
    "Alis Fiyati": "",
    "Maliyet (TL)": "",
    "Guncel Fiyat": "",
    "Guncel Getiri": "",
    "Net Kar-Zarar (tl)": "",
    "% Kar- Zarar": "",
    "SatisFiyati": "",
    "Satildi mi ?": ""
  },
  {
    "": "",
    "Adet": "",
    "Alis Fiyati": "",
    "Maliyet (TL)": "",
    "Guncel Fiyat": "",
    "Guncel Getiri": "",
    "Net Kar-Zarar (tl)": "",
    "% Kar- Zarar": "",
    "SatisFiyati": "",
    "Satildi mi ?": ""
  },
  {
    "": "",
    "Adet": "",
    "Alis Fiyati": "",
    "Maliyet (TL)": "",
    "Guncel Fiyat": "",
    "Guncel Getiri": "",
    "Net Kar-Zarar (tl)": "",
    "% Kar- Zarar": "",
    "SatisFiyati": "",
    "Satildi mi ?": ""
  },
  {
    "": "",
    "Adet": "",
    "Alis Fiyati": "",
    "Maliyet (TL)": "",
    "Guncel Fiyat": "",
    "Guncel Getiri": "",
    "Net Kar-Zarar (tl)": "",
    "% Kar- Zarar": "",
    "SatisFiyati": "",
    "Satildi mi ?": ""
  },
  {
    "": "",
    "Adet": "",
    "Alis Fiyati": "",
    "Maliyet (TL)": "",
    "Guncel Fiyat": "",
    "Guncel Getiri": "",
    "Net Kar-Zarar (tl)": "",
    "% Kar- Zarar": "",
    "SatisFiyati": "",
    "Satildi mi ?": ""
  },
  {
    "": "Toplam",
    "Adet": 0,
    "Alis Fiyati": 0,
    "Maliyet (TL)": 1848.31,
    "Guncel Fiyat": 0,
    "Guncel Getiri": 2609.48,
    "Net Kar-Zarar (tl)": 761.1700000000001,
    "% Kar- Zarar": 0.41181944587217517,
    "SatisFiyati": "",
    "Satildi mi ?": ""
  },
  {
    "": "",
    "Adet": "",
    "Alis Fiyati": "",
    "Maliyet (TL)": "",
    "Guncel Fiyat": "",
    "Guncel Getiri": "",
    "Net Kar-Zarar (tl)": "",
    "% Kar- Zarar": "",
    "SatisFiyati": "",
    "Satildi mi ?": ""
  },
  {
    "": "",
    "Adet": "",
    "Alis Fiyati": "",
    "Maliyet (TL)": "",
    "Guncel Fiyat": "",
    "Guncel Getiri": "",
    "Net Kar-Zarar (tl)": "",
    "% Kar- Zarar": "",
    "SatisFiyati": "",
    "Satildi mi ?": ""
  },
  {
    "": "",
    "Adet": "",
    "Alis Fiyati": "",
    "Maliyet (TL)": "",
    "Guncel Fiyat": "",
    "Guncel Getiri": "",
    "Net Kar-Zarar (tl)": "",
    "% Kar- Zarar": "",
    "SatisFiyati": "",
    "Satildi mi ?": ""
  },
  {
    "": "",
    "Adet": "",
    "Alis Fiyati": "",
    "Maliyet (TL)": "",
    "Guncel Fiyat": "x zx x",
    "Guncel Getiri": "",
    "Net Kar-Zarar (tl)": "",
    "% Kar- Zarar": "",
    "SatisFiyati": "",
    "Satildi mi ?": ""
  },
  {
    "": "",
    "Adet": "",
    "Alis Fiyati": "",
    "Maliyet (TL)": "",
    "Guncel Fiyat": "",
    "Guncel Getiri": "",
    "Net Kar-Zarar (tl)": "",
    "% Kar- Zarar": "",
    "SatisFiyati": "",
    "Satildi mi ?": ""
  },
  {
    "": "",
    "Adet": "",
    "Alis Fiyati": "",
    "Maliyet (TL)": "",
    "Guncel Fiyat": "",
    "Guncel Getiri": "",
    "Net Kar-Zarar (tl)": "",
    "% Kar- Zarar": "",
    "SatisFiyati": "",
    "Satildi mi ?": ""
  },
  {
    "": "",
    "Adet": "",
    "Alis Fiyati": "",
    "Maliyet (TL)": "",
    "Guncel Fiyat": "",
    "Guncel Getiri": "",
    "Net Kar-Zarar (tl)": "",
    "% Kar- Zarar": "",
    "SatisFiyati": "",
    "Satildi mi ?": false
  }
]